xssniffer/__init__.py
xssniffer/core.py
xssniffer/scanner.py
xssniffer-0.1.0.dist-info/LICENSE
xssniffer-0.1.0.dist-info/METADATA
xssniffer-0.1.0.dist-info/WHEEL
xssniffer-0.1.0.dist-info/entry_points.txt
xssniffer-0.1.0.dist-info/top_level.txt
xssniffer-0.1.0.dist-info/RECORD
