Metadata-Version: 2.1
Name: xssniffer
Version: 0.1.0
Summary: A package to find XSS vulnerabilities.
Home-page: https://github.com/yourusername/xssniffer
Author: Fidal
Author-email: mrfidal@proton.me
Classifier: Programming Language :: Python :: 3
Classifier: License :: OSI Approved :: MIT License
Classifier: Operating System :: OS Independent
Requires-Python: >=3.6
License-File: LICENSE
Requires-Dist: requests
